LICENSE
youtrack/__init__.py
youtrack/config.py
youtrack/connection.py
youtrack/import_helper.py
youtrack/youtrack.py
prima_youtrack-0.2.4.dist-info/LICENSE
prima_youtrack-0.2.4.dist-info/METADATA
prima_youtrack-0.2.4.dist-info/WHEEL
prima_youtrack-0.2.4.dist-info/top_level.txt
prima_youtrack-0.2.4.dist-info/zip-safe
prima_youtrack-0.2.4.dist-info/RECORD
